entity_microservice/__init__.py
entity_microservice/app.py
entity_microservice/health.py
entity_microservice-0.1.0.dist-info/WHEEL
entity_microservice-0.1.0.dist-info/METADATA
entity_microservice-0.1.0.dist-info/RECORD
