Metadata-Version: 2.1
Name: entity-microservice
Version: 0.1.0
Summary: 
Author: Sakshi Singla
Author-email: sakshi_singla@intuit.com
Requires-Python: >=3.7,<4.0
Classifier: Programming Language :: Python :: 3
Classifier: Programming Language :: Python :: 3.7
Classifier: Programming Language :: Python :: 3.8
Classifier: Programming Language :: Python :: 3.9
Requires-Dist: flask
